{
  "$schema": "https://developer.microsoft.com/json-schemas/fabric/item/report/definition/visualContainer/2.4.0/schema.json",
  "name": "5c345aecdbe7494a7b88",
  "position": {
    "x": 639.85714285714278,
    "y": 172.6349206349206,
    "z": 5000,
    "height": 281.11111111111109,
    "width": 623.33333333333337,
    "tabOrder": 4000
  },
  "visual": {
    "visualType": "lineChart",
    "query": {
      "queryState": {
        "Category": {
          "projections": [
            {
              "field": {
                "Column": {
                  "Expression": {
                    "SourceRef": {
                      "Entity": "Dim_Calendar_Ops"
                    }
                  },
                  "Property": "#Year"
                }
              },
              "queryRef": "Dim_Calendar_Ops.#Year",
              "nativeQueryRef": "#Year",
              "active": true
            },
            {
              "field": {
                "Column": {
                  "Expression": {
                    "SourceRef": {
                      "Entity": "Dim_Calendar_Ops"
                    }
                  },
                  "Property": "ShortMonth"
                }
              },
              "queryRef": "Dim_Calendar_Ops.ShortMonth",
              "nativeQueryRef": "ShortMonth",
              "active": true
            }
          ]
        },
        "Y": {
          "projections": [
            {
              "field": {
                "Measure": {
                  "Expression": {
                    "SourceRef": {
                      "Entity": "Mesuares New Turnover"
                    }
                  },
                  "Property": "% Turnover Unified"
                }
              },
              "queryRef": "Mesuares New Attrition.% Attrition Unified",
              "nativeQueryRef": "% Attrition Unified"
            }
          ]
        }
      }
    },
    "objects": {
      "valueAxis": [
        {
          "properties": {
            "show": {
              "expr": {
                "Literal": {
                  "Value": "true"
                }
              }
            },
            "fontSize": {
              "expr": {
                "Literal": {
                  "Value": "8D"
                }
              }
            },
            "bold": {
              "expr": {
                "Literal": {
                  "Value": "false"
                }
              }
            },
            "labelColor": {
              "solid": {
                "color": {
                  "expr": {
                    "Literal": {
                      "Value": "'#605E5C'"
                    }
                  }
                }
              }
            },
            "showAxisTitle": {
              "expr": {
                "Literal": {
                  "Value": "false"
                }
              }
            },
            "titleFontSize": {
              "expr": {
                "Literal": {
                  "Value": "9D"
                }
              }
            },
            "fontFamily": {
              "expr": {
                "Literal": {
                  "Value": "'Arial'"
                }
              }
            }
          }
        }
      ],
      "labels": [
        {
          "properties": {
            "show": {
              "expr": {
                "Literal": {
                  "Value": "true"
                }
              }
            },
            "optimizeLabelDisplay": {
              "expr": {
                "Literal": {
                  "Value": "false"
                }
              }
            },
            "color": {
              "solid": {
                "color": {
                  "expr": {
                    "Literal": {
                      "Value": "'#001F38'"
                    }
                  }
                }
              }
            },
            "fontFamily": {
              "expr": {
                "Literal": {
                  "Value": "'Arial'"
                }
              }
            },
            "bold": {
              "expr": {
                "Literal": {
                  "Value": "true"
                }
              }
            },
            "fontSize": {
              "expr": {
                "Literal": {
                  "Value": "8D"
                }
              }
            }
          }
        },
        {
          "properties": {
            "enableBackground": {
              "expr": {
                "Literal": {
                  "Value": "true"
                }
              }
            },
            "backgroundColor": {
              "solid": {
                "color": {
                  "expr": {
                    "ThemeDataColor": {
                      "ColorId": 3,
                      "Percent": 0
                    }
                  }
                }
              }
            },
            "backgroundTransparency": {
              "expr": {
                "Literal": {
                  "Value": "0L"
                }
              }
            },
            "color": {
              "solid": {
                "color": {
                  "expr": {
                    "ThemeDataColor": {
                      "ColorId": 0,
                      "Percent": 0
                    }
                  }
                }
              }
            }
          },
          "selector": {
            "metadata": ".measure.Total Tickets"
          }
        },
        {
          "properties": {
            "enableBackground": {
              "expr": {
                "Literal": {
                  "Value": "true"
                }
              }
            },
            "backgroundColor": {
              "solid": {
                "color": {
                  "expr": {
                    "ThemeDataColor": {
                      "ColorId": 4,
                      "Percent": 0
                    }
                  }
                }
              }
            },
            "backgroundTransparency": {
              "expr": {
                "Literal": {
                  "Value": "0L"
                }
              }
            },
            "color": {
              "solid": {
                "color": {
                  "expr": {
                    "ThemeDataColor": {
                      "ColorId": 0,
                      "Percent": 0
                    }
                  }
                }
              }
            }
          },
          "selector": {
            "metadata": ".measure.Backlog at Period End"
          }
        }
      ],
      "categoryAxis": [
        {
          "properties": {
            "show": {
              "expr": {
                "Literal": {
                  "Value": "true"
                }
              }
            },
            "fontSize": {
              "expr": {
                "Literal": {
                  "Value": "8D"
                }
              }
            },
            "bold": {
              "expr": {
                "Literal": {
                  "Value": "false"
                }
              }
            },
            "labelColor": {
              "solid": {
                "color": {
                  "expr": {
                    "Literal": {
                      "Value": "'#605E5C'"
                    }
                  }
                }
              }
            },
            "showAxisTitle": {
              "expr": {
                "Literal": {
                  "Value": "false"
                }
              }
            },
            "fontFamily": {
              "expr": {
                "Literal": {
                  "Value": "'Arial'"
                }
              }
            }
          }
        }
      ],
      "general": [
        {
          "properties": {
            "responsive": {
              "expr": {
                "Literal": {
                  "Value": "false"
                }
              }
            }
          }
        }
      ],
      "legend": [
        {
          "properties": {
            "show": {
              "expr": {
                "Literal": {
                  "Value": "true"
                }
              }
            },
            "fontSize": {
              "expr": {
                "Literal": {
                  "Value": "10D"
                }
              }
            },
            "labelColor": {
              "solid": {
                "color": {
                  "expr": {
                    "ThemeDataColor": {
                      "ColorId": 1,
                      "Percent": 0
                    }
                  }
                }
              }
            }
          }
        }
      ],
      "zoom": [
        {
          "properties": {
            "show": {
              "expr": {
                "Literal": {
                  "Value": "false"
                }
              }
            }
          }
        }
      ],
      "dataPoint": [
        {
          "properties": {
            "fill": {
              "solid": {
                "color": {
                  "expr": {
                    "Literal": {
                      "Value": "'#064789'"
                    }
                  }
                }
              }
            }
          }
        },
        {
          "properties": {
            "fill": {
              "solid": {
                "color": {
                  "expr": {
                    "ThemeDataColor": {
                      "ColorId": 3,
                      "Percent": 0
                    }
                  }
                }
              }
            }
          },
          "selector": {
            "metadata": ".measure.Total Tickets"
          }
        },
        {
          "properties": {
            "fill": {
              "solid": {
                "color": {
                  "expr": {
                    "ThemeDataColor": {
                      "ColorId": 4,
                      "Percent": 0.2
                    }
                  }
                }
              }
            }
          },
          "selector": {
            "metadata": ".measure.Backlog at Period End"
          }
        },
        {
          "properties": {
            "fill": {
              "solid": {
                "color": {
                  "expr": {
                    "ThemeDataColor": {
                      "ColorId": 8,
                      "Percent": 0
                    }
                  }
                }
              }
            }
          },
          "selector": {
            "metadata": "Mesuares New Attrition.% Attrition Unified"
          }
        }
      ],
      "lineStyles": [
        {
          "properties": {
            "strokeWidth": {
              "expr": {
                "Literal": {
                  "Value": "2D"
                }
              }
            },
            "showMarker": {
              "expr": {
                "Literal": {
                  "Value": "true"
                }
              }
            },
            "lineChartType": {
              "expr": {
                "Literal": {
                  "Value": "'linear'"
                }
              }
            },
            "areaShow": {
              "expr": {
                "Literal": {
                  "Value": "false"
                }
              }
            }
          }
        }
      ],
      "y1AxisReferenceLine": [
        {
          "properties": {
            "show": {
              "expr": {
                "Literal": {
                  "Value": "true"
                }
              }
            },
            "displayName": {
              "expr": {
                "Literal": {
                  "Value": "'Threshold'"
                }
              }
            },
            "value": {
              "expr": {
                "Literal": {
                  "Value": "0.035D"
                }
              }
            },
            "transparency": {
              "expr": {
                "Literal": {
                  "Value": "62D"
                }
              }
            },
            "dataLabelShow": {
              "expr": {
                "Literal": {
                  "Value": "true"
                }
              }
            },
            "dataLabelDisplayUnits": {
              "expr": {
                "Literal": {
                  "Value": "1D"
                }
              }
            },
            "dataLabelText": {
              "expr": {
                "Literal": {
                  "Value": "'ValueAndName'"
                }
              }
            },
            "shadeShow": {
              "expr": {
                "Literal": {
                  "Value": "true"
                }
              }
            },
            "shadeTransparency": {
              "expr": {
                "Literal": {
                  "Value": "80D"
                }
              }
            },
            "shadeColorMatchStroke": {
              "expr": {
                "Literal": {
                  "Value": "false"
                }
              }
            },
            "shadeRegion": {
              "expr": {
                "Literal": {
                  "Value": "'after'"
                }
              }
            },
            "shadeColor": {
              "solid": {
                "color": {
                  "expr": {
                    "Literal": {
                      "Value": "'#E5A8A8'"
                    }
                  }
                }
              }
            }
          },
          "selector": {
            "id": "1"
          }
        }
      ],
      "markers": [
        {
          "properties": {
            "borderShow": {
              "expr": {
                "Literal": {
                  "Value": "true"
                }
              }
            },
            "borderColor": {
              "solid": {
                "color": {
                  "expr": {
                    "ThemeDataColor": {
                      "ColorId": 0,
                      "Percent": 0
                    }
                  }
                }
              }
            }
          }
        }
      ]
    },
    "visualContainerObjects": {
      "title": [
        {
          "properties": {
            "text": {
              "expr": {
                "Literal": {
                  "Value": "'Monthly Turnover Trend (%)'"
                }
              }
            },
            "titleWrap": {
              "expr": {
                "Literal": {
                  "Value": "true"
                }
              }
            },
            "fontColor": {
              "solid": {
                "color": {
                  "expr": {
                    "Literal": {
                      "Value": "'#001F38'"
                    }
                  }
                }
              }
            },
            "alignment": {
              "expr": {
                "Literal": {
                  "Value": "'left'"
                }
              }
            },
            "fontSize": {
              "expr": {
                "Literal": {
                  "Value": "12D"
                }
              }
            },
            "bold": {
              "expr": {
                "Literal": {
                  "Value": "true"
                }
              }
            },
            "fontFamily": {
              "expr": {
                "Literal": {
                  "Value": "'Arial'"
                }
              }
            }
          }
        }
      ],
      "background": [
        {
          "properties": {
            "show": {
              "expr": {
                "Literal": {
                  "Value": "true"
                }
              }
            },
            "transparency": {
              "expr": {
                "Literal": {
                  "Value": "0D"
                }
              }
            }
          }
        }
      ],
      "border": [
        {
          "properties": {
            "show": {
              "expr": {
                "Literal": {
                  "Value": "true"
                }
              }
            },
            "color": {
              "solid": {
                "color": {
                  "expr": {
                    "Literal": {
                      "Value": "'#E3E8EB'"
                    }
                  }
                }
              }
            },
            "radius": {
              "expr": {
                "Literal": {
                  "Value": "5D"
                }
              }
            },
            "width": {
              "expr": {
                "Literal": {
                  "Value": "1D"
                }
              }
            }
          }
        }
      ],
      "subTitle": [
        {
          "properties": {
            "show": {
              "expr": {
                "Literal": {
                  "Value": "true"
                }
              }
            },
            "fontColor": {
              "solid": {
                "color": {
                  "expr": {
                    "ThemeDataColor": {
                      "ColorId": 0,
                      "Percent": -0.6
                    }
                  }
                }
              }
            },
            "alignment": {
              "expr": {
                "Literal": {
                  "Value": "'left'"
                }
              }
            },
            "fontSize": {
              "expr": {
                "Literal": {
                  "Value": "10D"
                }
              }
            },
            "text": {
              "expr": {
                "Literal": {
                  "Value": "'How the turnover rate has moved month by month against the expected threshold.'"
                }
              }
            },
            "fontFamily": {
              "expr": {
                "Literal": {
                  "Value": "'Arial'"
                }
              }
            }
          }
        }
      ],
      "divider": [
        {
          "properties": {
            "show": {
              "expr": {
                "Literal": {
                  "Value": "false"
                }
              }
            },
            "color": {
              "solid": {
                "color": {
                  "expr": {
                    "ThemeDataColor": {
                      "ColorId": 1,
                      "Percent": 0
                    }
                  }
                }
              }
            }
          }
        }
      ],
      "spacing": [
        {
          "properties": {
            "customizeSpacing": {
              "expr": {
                "Literal": {
                  "Value": "true"
                }
              }
            },
            "verticalSpacing": {
              "expr": {
                "Literal": {
                  "Value": "0D"
                }
              }
            },
            "spaceBelowSubTitle": {
              "expr": {
                "Literal": {
                  "Value": "10D"
                }
              }
            }
          }
        }
      ],
      "dropShadow": [
        {
          "properties": {
            "show": {
              "expr": {
                "Literal": {
                  "Value": "false"
                }
              }
            },
            "preset": {
              "expr": {
                "Literal": {
                  "Value": "'Center'"
                }
              }
            },
            "color": {
              "solid": {
                "color": {
                  "expr": {
                    "ThemeDataColor": {
                      "ColorId": 2,
                      "Percent": 0
                    }
                  }
                }
              }
            },
            "transparency": {
              "expr": {
                "Literal": {
                  "Value": "70L"
                }
              }
            },
            "shadowSpread": {
              "expr": {
                "Literal": {
                  "Value": "3L"
                }
              }
            },
            "shadowBlur": {
              "expr": {
                "Literal": {
                  "Value": "15L"
                }
              }
            },
            "angle": {
              "expr": {
                "Literal": {
                  "Value": "0L"
                }
              }
            },
            "shadowDistance": {
              "expr": {
                "Literal": {
                  "Value": "0L"
                }
              }
            }
          }
        }
      ],
      "visualTooltip": [
        {
          "properties": {
            "show": {
              "expr": {
                "Literal": {
                  "Value": "false"
                }
              }
            }
          }
        }
      ],
      "visualHeader": [
        {
          "properties": {
            "show": {
              "expr": {
                "Literal": {
                  "Value": "false"
                }
              }
            }
          }
        }
      ],
      "padding": [
        {
          "properties": {
            "top": {
              "expr": {
                "Literal": {
                  "Value": "10D"
                }
              }
            },
            "left": {
              "expr": {
                "Literal": {
                  "Value": "10D"
                }
              }
            },
            "right": {
              "expr": {
                "Literal": {
                  "Value": "10D"
                }
              }
            }
          }
        }
      ]
    },
    "drillFilterOtherVisuals": true
  },
  "filterConfig": {
    "filters": [
      {
        "name": "d0d8f3caab7d6b645d3b",
        "field": {
          "Column": {
            "Expression": {
              "SourceRef": {
                "Entity": "Dim_Calendar_Ops"
              }
            },
            "Property": "Date"
          }
        },
        "type": "Categorical",
        "filter": {
          "Version": 2,
          "From": [
            {
              "Name": "l",
              "Entity": "LocalDateTable_81738fc8-8a5c-45e7-8afd-d0cf32e940c6",
              "Type": 0
            }
          ],
          "Where": [
            {
              "Condition": {
                "Not": {
                  "Expression": {
                    "In": {
                      "Expressions": [
                        {
                          "Column": {
                            "Expression": {
                              "SourceRef": {
                                "Source": "l"
                              }
                            },
                            "Property": "Month"
                          }
                        }
                      ],
                      "Values": [
                        [
                          {
                            "Literal": {
                              "Value": "null"
                            }
                          }
                        ]
                      ]
                    }
                  }
                }
              }
            }
          ]
        },
        "howCreated": "User",
        "objects": {
          "general": [
            {
              "properties": {
                "isInvertedSelectionMode": {
                  "expr": {
                    "Literal": {
                      "Value": "true"
                    }
                  }
                }
              }
            }
          ]
        }
      }
    ]
  }
}